play_sounds/__init__.py
play_sounds/base.py
play_sounds/bell.py
play_sounds/proc.py
play_sounds/wrap.py
play_sounds-0.6.0.dist-info/LICENSE
play_sounds-0.6.0.dist-info/METADATA
play_sounds-0.6.0.dist-info/WHEEL
play_sounds-0.6.0.dist-info/top_level.txt
play_sounds-0.6.0.dist-info/RECORD
