Metadata-Version: 2.1
Name: play_sounds
Version: 0.6.0
Summary: 🔊 Play music and sounds in your Python scripts
Home-page: https://github.com/alexdelorenzo/play_sounds
Author: Alex DeLorenzo
License: LGPL-3.0
Requires-Python: >=3.6
License-File: LICENSE
Requires-Dist: anyio ==3.0.1
Requires-Dist: boombox ==0.56
Requires-Dist: playsound
Requires-Dist: PyObjc >=6.2.2 ; sys_platform == "darwin"
